bluecurrent_api/__init__.py
bluecurrent_api/client.py
bluecurrent_api/exceptions.py
bluecurrent_api/py.typed
bluecurrent_api/types.py
bluecurrent_api/utils.py
bluecurrent_api/websocket.py
bluecurrent_api-1.3.2.dist-info/licenses/LICENSE
bluecurrent_api-1.3.2.dist-info/METADATA
bluecurrent_api-1.3.2.dist-info/WHEEL
bluecurrent_api-1.3.2.dist-info/top_level.txt
bluecurrent_api-1.3.2.dist-info/RECORD
