Metadata-Version: 2.4
Name: bluecurrent-api
Version: 1.3.2
Summary: A wrapper for the Blue Current websocket api
Author-email: Floris272 <florispuijk@outlook.com>
Maintainer-email: jtodorova23 <juliana.todorova@bluecurrent.nl>
License: MIT
Project-URL: Homepage, https://github.com/bluecurrent/HomeAssistantAPI
Project-URL: Bug Tracker, https://github.com/bluecurrent/HomeAssistantAPI/issues
Classifier: Programming Language :: Python :: 3
Classifier: License :: OSI Approved :: MIT License
Classifier: Operating System :: OS Independent
Requires-Python: >=3.11
License-File: LICENSE
Requires-Dist: websockets<16.0.0,>=15.0
Dynamic: license-file
